Workbook

Sheet 2026 Budget
A1: HealthRate
B3: 1 | C3: 2 | D3: 3 | E3: 4 | F3: 5 | G3: 6 | H3: 7 | I3: 8 | J3: 9 | K3: 10 | L3: 11 | M3: 12 | N3: SUBTOTALS
A4: OVERHEAD
A5: Rent / Meeting Space | B5: 0 | C5: 0 | D5: 0 | E5: 0 | F5: 0 | G5: 0 | H5: 0 | I5: 0 | J5: 0 | K5: 0 | L5: 0 | M5: 0 | N5: =SUM(B5:M5) -> 0
A6: Utiities (including cell phones) | B6: 700 | C6: 700 | D6: 700 | E6: 700 | F6: 700 | G6: 700 | H6: 700 | I6: 700 | J6: 700 | K6: 700 | L6: 700 | M6: 700 | N6: =SUM(B6:M6) -> 8400
A7: Software & Hardware | B7: 500 | C7: 500 | D7: 500 | E7: 500 | F7: 500 | G7: 500 | H7: 500 | I7: 500 | J7: 500 | K7: 500 | L7: 500 | M7: 500 | N7: =SUM(B7:M7) -> 6000
A8: SUBTOTAL | B8: =SUM(B5:B7) -> 1200 | C8: =SUM(C5:C7) -> 1200 | D8: =SUM(D5:D7) -> 1200 | E8: =SUM(E5:E7) -> 1200 | F8: =SUM(F5:F7) -> 1200 | G8: =SUM(G5:G7) -> 1200 | H8: =SUM(H5:H7) -> 1200 | I8: =SUM(I5:I7) -> 1200 | ... N8: =SUM(N5:N7) -> 14400
A10: PEOPLE
A11: Payroll - Loaded (tax and benefits) | B11: 45000 | C11: 45000 | D11: 45000 | E11: 65000 | F11: 65000 | G11: 65000 | H11: 65000 | I11: 65000 | J11: 65000 | K11: 85000 | L11: 85000 | M11: 85000 | N11: =SUM(B11:M11) -> 780000
A12: New Payroll (board expense) | B12: 0 | C12: 0 | D12: 0 | E12: 0 | F12: 0 | G12: 20000 | H12: 0 | I12: 0 | J12: 0 | K12: 0 | L12: 0 | M12: 20000 | N12: =SUM(B12:M12) -> 40000
A13: Hourly (UI & Dan) | B13: 0 | C13: 0 | D13: 0 | E13: 0 | F13: 0 | G13: 10000 | H13: 10000 | I13: 10000 | J13: 10000 | K13: 10000 | L13: 10000 | M13: 10000 | N13: =SUM(B13:M13) -> 70000
A14: SUBTOTAL | B14: =SUM(B11:B13) -> 45000 | C14: =SUM(C11:C13) -> 45000 | D14: =SUM(D11:D13) -> 45000 | E14: =SUM(E11:E13) -> 65000 | F14: =SUM(F11:F13) -> 65000 | G14: =SUM(G11:G13) -> 95000 | H14: =SUM(H11:H13) -> 75000 | I14: =SUM(I11:I13) -> 75000 | ... N14: =SUM(N11:N13) -> 890000
A16: SERVICES
A17: Legal fees | B17: 1500 | C17: 1500 | D17: 1500 | E17: 1500 | F17: 1500 | G17: 1500 | H17: 1500 | I17: 1500 | J17: 1500 | K17: 1500 | L17: 1500 | M17: 1500 | N17: =SUM(B17:M17) -> 18000
A18: Insurance | B18: 0 | C18: 8000 | D18: 0 | E18: 0 | F18: 0 | G18: 0 | H18: 0 | I18: 0 | J18: 0 | K18: 8000 | L18: 0 | M18: 0 | N18: =SUM(B18:M18) -> 16000
A19: Other PS, filing fees, etc | B19: 1000 | C19: 1000 | D19: 1000 | E19: 1000 | F19: 1000 | G19: 1000 | H19: 1000 | I19: 1000 | J19: 1000 | K19: 1000 | L19: 1000 | M19: 1000 | N19: =SUM(B19:M19) -> 12000
A20: SUBTOTAL | B20: =SUM(B17:B19) -> 2500 | C20: =SUM(C17:C19) -> 10500 | D20: =SUM(D17:D19) -> 2500 | E20: =SUM(E17:E19) -> 2500 | F20: =SUM(F17:F19) -> 2500 | G20: =SUM(G17:G19) -> 2500 | H20: =SUM(H17:H19) -> 2500 | I20: =SUM(I17:I19) -> 2500 | ... N20: =SUM(N17:N19) -> 46000
A22: PRODUCT
A23: Data Acquisition - IPD, Milliman, Fair, AMS or similar | B23: 0 | C23: 0 | D23: 0 | E23: 0 | F23: 0 | G23: 0 | H23: 0 | I23: 0 | J23: 0 | K23: 0 | L23: 0 | M23: 0 | N23: =SUM(B23:M23) -> 0
A24: Environment / Servers | B24: 400 | C24: 400 | D24: 1000 | E24: 1000 | F24: 1000 | G24: 1000 | H24: 1000 | I24: 1000 | J24: 2000 | K24: 2000 | L24: 2000 | M24: 2000 | N24: =SUM(B24:M24) -> 14800
A25: SUBTOTAL | B25: =SUM(B23:B24) -> 400 | C25: =SUM(C23:C24) -> 400 | D25: =SUM(D23:D24) -> 1000 | E25: =SUM(E23:E24) -> 1000 | F25: =SUM(F23:F24) -> 1000 | G25: =SUM(G23:G24) -> 1000 | H25: =SUM(H23:H24) -> 1000 | I25: =SUM(I23:I24) -> 1000 | ... N25: =SUM(N23:N24) -> 14800
A27: MARKETING
A28: Ongoing Marketing Expenses | B28: 15000 | C28: 15000 | D28: 15000 | E28: 15000 | F28: 15000 | G28: 15000 | H28: 15000 | I28: 15000 | J28: 15000 | K28: 15000 | L28: 15000 | M28: 15000 | N28: =SUM(B28:M28) -> 180000
A29: Conferences / Travel | B29: 1000 | C29: 1000 | D29: 1000 | E29: 1000 | F29: 1000 | G29: 1000 | H29: 1000 | I29: 1000 | J29: 1000 | K29: 1000 | L29: 1000 | M29: 1000 | N29: =SUM(B29:M29) -> 12000
A30: SUBTOTAL | B30: =SUM(B28:B29) -> 16000 | C30: =SUM(C28:C29) -> 16000 | D30: =SUM(D28:D29) -> 16000 | E30: =SUM(E28:E29) -> 16000 | F30: =SUM(F28:F29) -> 16000 | G30: =SUM(G28:G29) -> 16000 | H30: =SUM(H28:H29) -> 16000 | I30: =SUM(I28:I29) -> 16000 | ... N30: =SUM(N28:N29) -> 192000
A32: OTHER SG&A
A33: Petty Cash / Contingency | B33: 1500 | C33: 1500 | D33: 1500 | E33: 1500 | F33: 1500 | G33: 1500 | H33: 1500 | I33: 1500 | J33: 1500 | K33: 1500 | L33: 1500 | M33: 1500 | N33: =SUM(B33:M33) -> 18000
A34: SUBTOTAL | B34: =B33 -> 1500 | C34: =C33 -> 1500 | D34: =D33 -> 1500 | E34: =E33 -> 1500 | F34: =F33 -> 1500 | G34: =G33 -> 1500 | H34: =H33 -> 1500 | I34: =I33 -> 1500 | ... M34: =M33 -> 1500 | N34: =SUM(B34:M34) -> 18000
A36: TOTAL | B36: =B8+B14+B20+B25+B30+B34 -> 66600 | C36: =C8+C14+C20+C25+C30+C34 -> 74600 | D36: =D8+D14+D20+D25+D30+D34 -> 67200 | E36: =E8+E14+E20+E25+E30+E34 -> 87200 | F36: =F8+F14+F20+F25+F30+F34 -> 87200 | G36: =G8+G14+G20+G25+G30+G34 -> 117200 | H36: =H8+H14+H20+H25+H30+H34 -> 97200 | I36: =I8+I14+I20+I25+I30+I34 -> 97200 | ... M36: =M8+M14+M20+M25+M30+M34 -> 138200
A39: Running Total | B39: =B36 -> 66600 | C39: =B36+C36 -> 141200 | D39: =C39+D36 -> 208400 | E39: =D39+E36 -> 295600 | F39: =E39+F36 -> 382800 | G39: =F39+G36 -> 500000 | H39: =G39+H36 -> 597200 | I39: =H39+I36 -> 694400 | J39: =I39+J36 -> 792600 | K39: =J39+K36 -> 918800 | ... M39: =L39+M36 -> 1175200 | N39: =N8+N14+N20+N25+N30+N34 -> 1175200
A42: REVENUE
A43: SaaS Subscriptions | B43: ='2026 HQ Pipeline'!B21 -> 0 | C43: ='2026 HQ Pipeline'!C21 -> 11000 | D43: ='2026 HQ Pipeline'!D21 -> 185000 | E43: ='2026 HQ Pipeline'!E21 -> 540000 | F43: ='2026 HQ Pipeline'!F21 -> 630000 | G43: ='2026 HQ Pipeline'!G21 -> 1130000 | H43: ='2026 HQ Pipeline'!H21 -> 1130000 | I43: ='2026 HQ Pipeline'!I21 -> 1130000 | ... M43: ='2026 HQ Pipeline'!M21 -> 1130000 | N43: =SUM(B43:M43) -> 9276000
A45: P&L | N45: =N43-N39 -> 8100800
A46: Margin | N46: =(N43-N39)/N43 -> 0.87330746

Sheet 2026 HQ Pipeline
A1: HealthRate
A3: EXISTING PIPELINE ONLY | B3: 1 | C3: 2 | D3: 3 | E3: 4 | F3: 5 | G3: 6 | H3: 7 | I3: 8 | J3: 9 | K3: 10 | L3: 11 | M3: 12 | N3: SUBTOTALS
A4: REVENUE - CONSERVATIVE
A5: Harbor Health | D5: 10000 | E5: 10000 | F5: 10000 | G5: 10000 | H5: 10000 | I5: 10000 | J5: 10000 | K5: 10000 | L5: 10000 | M5: 10000 | N5: =SUM(B5:M5) -> 100000
A6: Reflect | C6: 10000 | D6: 10000 | E6: 10000 | F6: 25000 | G6: 25000 | H6: 25000 | I6: 25000 | J6: 25000 | K6: 25000 | L6: 25000 | M6: 25000 | N6: =SUM(B6:M6) -> 230000
A7: Portico | D7: 25000 | E7: 25000 | F7: 25000 | G7: 25000 | H7: 25000 | I7: 25000 | J7: 25000 | K7: 25000 | L7: 25000 | M7: 25000 | N7: =SUM(B7:M7) -> 250000
A8: Beyond Risk | D8: 10000 | E8: 10000 | F8: 10000 | G8: 10000 | H8: 10000 | I8: 10000 | J8: 10000 | K8: 10000 | L8: 10000 | M8: 10000 | N8: =SUM(B8:M8) -> 100000
A9: HPI | D9: 25000 | E9: 25000 | F9: 25000 | G9: 25000 | H9: 25000 | I9: 25000 | J9: 25000 | K9: 25000 | L9: 25000 | M9: 25000 | N9: =SUM(B9:M9) -> 250000
A10: Aegle | D10: 10000 | E10: 10000 | F10: 10000 | G10: 10000 | H10: 10000 | I10: 10000 | J10: 10000 | K10: 10000 | L10: 10000 | M10: 10000 | N10: =SUM(B10:M10) -> 100000
A11: Premera | E11: 150000 | F11: 150000 | G11: 150000 | H11: 150000 | I11: 150000 | J11: 150000 | K11: 150000 | L11: 150000 | M11: 150000 | N11: =SUM(B11:M11) -> 1350000
A12: MVP - VERBALLY SOLD | D12: 75000 | E12: 75000 | F12: 75000 | G12: 75000 | H12: 75000 | I12: 75000 | J12: 75000 | K12: 75000 | L12: 75000 | M12: 75000 | N12: =SUM(B12:M12) -> 750000
A13: Point32 | E13: 200000 | F13: 200000 | G13: 200000 | H13: 200000 | I13: 200000 | J13: 200000 | K13: 200000 | L13: 200000 | M13: 200000 | N13: =SUM(B13:M13) -> 1800000
A14: ERISA Litigation Fees (Confidential) - SOLD | B14: 1000 | C14: 1000 | D14: 10000 | E14: 10000 | F14: 10000 | G14: 10000 | H14: 10000 | I14: 10000 | J14: 10000 | K14: 10000 | L14: 10000 | M14: 10000 | N14: =SUM(B14:M14) -> 102000 | P14: Estimating only expert fees at this time, not new clients driven
A15: NOMI | F15: 25000 | G15: 25000 | H15: 25000 | I15: 25000 | J15: 25000 | K15: 25000 | L15: 25000 | M15: 25000 | N15: =SUM(B15:M15) -> 200000
A16: Karias - VERBALLY SOLD | D16: 10000 | E16: 10000 | F16: 10000 | G16: 10000 | H16: 10000 | I16: 10000 | J16: 10000 | K16: 10000 | L16: 10000 | M16: 10000 | N16: =SUM(B16:M16) -> 100000
A17: Blue Shield California | F17: 50000 | G17: 50000 | H17: 50000 | I17: 50000 | J17: 50000 | K17: 50000 | L17: 50000 | M17: 50000 | N17: =SUM(B17:M17) -> 400000
A18: IBC | G18: 500000 | H18: 500000 | I18: 500000 | J18: 500000 | K18: 500000 | L18: 500000 | M18: 500000 | N18: =SUM(B18:M18) -> 3500000
A19: Atrio | E19: 5000 | F19: 5000 | G19: 5000 | H19: 5000 | I19: 5000 | J19: 5000 | K19: 5000 | L19: 5000 | M19: 5000 | N19: =SUM(B19:M19) -> 45000
C21: =SUM(C5:C17) -> 11000 | D21: =SUM(D5:D19) -> 185000 | E21: =SUM(E5:E19) -> 540000 | F21: =SUM(F5:F19) -> 630000 | G21: =SUM(G5:G19) -> 1130000 | H21: =SUM(H5:H19) -> 1130000 | I21: =SUM(I5:I19) -> 1130000 | J21: =SUM(J5:J19) -> 1130000 | K21: =SUM(K5:K19) -> 1130000 | ... M21: =SUM(M5:M19) -> 1130000 | N21: =SUM(B21:M21) -> 9276000
